libzac/__init__.py
libzac/bitfield.py
libzac/dsp.py
libzac/e.py
libzac/io.py
libzac/logic.py
libzac/math.py
libzac/plt.py
libzac/reg.py
libzac-0.2.2.dist-info/licenses/LICENSE
libzac-0.2.2.dist-info/METADATA
libzac-0.2.2.dist-info/WHEEL
libzac-0.2.2.dist-info/top_level.txt
libzac-0.2.2.dist-info/RECORD
