Metadata-Version: 2.4
Name: libzac
Version: 0.2.2
Summary: A private use library
Author-email: ZinGer_KyoN <zinger.kyon@gmail.com>
License: MIT License
Classifier: Programming Language :: Python :: 3
Classifier: License :: OSI Approved :: MIT License
Classifier: Operating System :: OS Independent
Requires-Python: >=3.7
License-File: LICENSE
Requires-Dist: numpy
Requires-Dist: matplotlib
Requires-Dist: pandas
Requires-Dist: packaging
Requires-Dist: xlrd
Requires-Dist: openpyxl
Requires-Dist: classutilities
Requires-Dist: mplcursors
Requires-Dist: scipy
Requires-Dist: soundfile
Requires-Dist: tqdm
Dynamic: license-file
